pyim/__init__.py
pyim/model.py
pyim/align/__init__.py
pyim/align/util.py
pyim/align/pipelines/__init__.py
pyim/align/pipelines/base.py
pyim/align/pipelines/nextera.py
pyim/align/pipelines/shear_splink.py
pyim/annotate/__init__.py
pyim/annotate/filter_.py
pyim/annotate/metadata.py
pyim/annotate/util.py
pyim/annotate/annotators/__init__.py
pyim/annotate/annotators/base.py
pyim/annotate/annotators/rbm.py
pyim/annotate/annotators/window.py
pyim/cis/__init__.py
pyim/cis/util.py
pyim/cis/callers/__init__.py
pyim/cis/callers/base.py
pyim/cis/callers/cimpl.py
pyim/external/__init__.py
pyim/external/bowtie2.py
pyim/external/cutadapt.py
pyim/external/util.py
pyim/main/__init__.py
pyim/main/pyim_align.py
pyim/main/pyim_annotate.py
pyim/main/pyim_bed.py
pyim/main/pyim_cis.py
pyim/main/pyim_demultiplex.py
pyim/main/pyim_merge.py
pyim/main/pyim_split.py
pyim/util/__init__.py
pyim/util/frozendict.py
pyim/util/path.py
pyim/util/rpy2.py
pyim/util/tabix.py
pyim-0.2.1.dist-info/DESCRIPTION.rst
pyim-0.2.1.dist-info/METADATA
pyim-0.2.1.dist-info/RECORD
pyim-0.2.1.dist-info/WHEEL
pyim-0.2.1.dist-info/entry_points.txt
pyim-0.2.1.dist-info/metadata.json
pyim-0.2.1.dist-info/top_level.txt
